[
  {
    "time": "14/02/28 18時",
    "star1": {
      "price": "2,000",
      "exhibits": "6 "
    },
    "star0": {
      "price": "3,500",
      "exhibits": "5 "
    },
    "star3": {
      "price": "5,000",
      "exhibits": "11 "
    },
    "star2": {
      "price": "3,300",
      "exhibits": "12 "
    },
    "id": "1640"
  },
  {
    "time": "14/02/27 19時",
    "star1": {
      "price": "3,300",
      "exhibits": "5 "
    },
    "star0": {
      "price": "6,000",
      "exhibits": "1 "
    },
    "star3": {
      "price": "6,500",
      "exhibits": "12 "
    },
    "star2": {
      "price": "3,300",
      "exhibits": "19 "
    },
    "id": "1640"
  },
  {
    "time": "14/02/26 15時",
    "star1": {
      "price": "3,000",
      "exhibits": "11 "
    },
    "star0": {
      "price": "4,000",
      "exhibits": "3 "
    },
    "star3": {
      "price": "6,000",
      "exhibits": "16 "
    },
    "star2": {
      "price": "3,300",
      "exhibits": "26 "
    },
    "id": "1640"
  },
  {
    "time": "14/02/26 03時",
    "star1": {
      "price": "3,300",
      "exhibits": "10 "
    },
    "star0": {
      "price": "4,000",
      "exhibits": "2 "
    },
    "star3": {
      "price": "7,000",
      "exhibits": "12 "
    },
    "star2": {
      "price": "3,300",
      "exhibits": "22 "
    },
    "id": "1640"
  },
  {
    "time": "14/02/25 15時",
    "star1": {
      "price": "3,300",
      "exhibits": "23 "
    },
    "star0": {
      "price": "4,000",
      "exhibits": "4 "
    },
    "star3": {
      "price": "7,500",
      "exhibits": "7 "
    },
    "star2": {
      "price": "3,300",
      "exhibits": "25 "
    },
    "id": "1640"
  },
  {
    "time": "14/02/25 03時",
    "star1": {
      "price": "3,700",
      "exhibits": "16 "
    },
    "star0": {
      "price": "4,000",
      "exhibits": "5 "
    },
    "star3": {
      "price": "7,500",
      "exhibits": "8 "
    },
    "star2": {
      "price": "3,300",
      "exhibits": "28 "
    },
    "id": "1640"
  },
  {
    "time": "14/02/24 15時",
    "star1": {
      "price": "3,700",
      "exhibits": "20 "
    },
    "star0": {
      "price": "3,550",
      "exhibits": "8 "
    },
    "star3": {
      "price": "7,700",
      "exhibits": "5 "
    },
    "star2": {
      "price": "3,400",
      "exhibits": "16 "
    },
    "id": "1640"
  },
  {
    "time": "14/02/24 03時",
    "star1": {
      "price": "3,700",
      "exhibits": "23 "
    },
    "star0": {
      "price": "3,980",
      "exhibits": "7 "
    },
    "star3": {
      "price": "8,000",
      "exhibits": "4 "
    },
    "star2": {
      "price": "3,400",
      "exhibits": "17 "
    },
    "id": "1640"
  },
  {
    "time": "14/02/23 15時",
    "star1": {
      "price": "3,690",
      "exhibits": "34 "
    },
    "star0": {
      "price": "3,980",
      "exhibits": "4 "
    },
    "star3": {
      "price": "5,480",
      "exhibits": "4 "
    },
    "star2": {
      "price": "3,560",
      "exhibits": "10 "
    },
    "id": "1640"
  },
  {
    "time": "14/02/23 03時",
    "star1": {
      "price": "4,000",
      "exhibits": "18 "
    },
    "star0": {
      "price": "--",
      "exhibits": "--"
    },
    "star3": {
      "price": "5,480",
      "exhibits": "5 "
    },
    "star2": {
      "price": "3,740",
      "exhibits": "17 "
    },
    "id": "1640"
  },
  {
    "time": "14/02/22 15時",
    "star1": {
      "price": "4,000",
      "exhibits": "33 "
    },
    "star0": {
      "price": "4,000",
      "exhibits": "1 "
    },
    "star3": {
      "price": "4,400",
      "exhibits": "8 "
    },
    "star2": {
      "price": "3,680",
      "exhibits": "19 "
    },
    "id": "1640"
  },
  {
    "time": "14/02/22 03時",
    "star1": {
      "price": "4,000",
      "exhibits": "24 "
    },
    "star0": {
      "price": "3,990",
      "exhibits": "2 "
    },
    "star3": {
      "price": "4,680",
      "exhibits": "15 "
    },
    "star2": {
      "price": "4,000",
      "exhibits": "11 "
    },
    "id": "1640"
  },
  {
    "time": "14/02/21 15時",
    "star1": {
      "price": "4,090",
      "exhibits": "20 "
    },
    "star0": {
      "price": "3,880",
      "exhibits": "2 "
    },
    "star3": {
      "price": "4,800",
      "exhibits": "15 "
    },
    "star2": {
      "price": "4,000",
      "exhibits": "19 "
    },
    "id": "1640"
  },
  {
    "time": "14/02/21 03時",
    "star1": {
      "price": "4,100",
      "exhibits": "17 "
    },
    "star0": {
      "price": "4,100",
      "exhibits": "1 "
    },
    "star3": {
      "price": "4,800",
      "exhibits": "15 "
    },
    "star2": {
      "price": "4,100",
      "exhibits": "13 "
    },
    "id": "1640"
  },
  {
    "time": "14/02/20 15時",
    "star1": {
      "price": "4,300",
      "exhibits": "14 "
    },
    "star0": {
      "price": "--",
      "exhibits": "--"
    },
    "star3": {
      "price": "5,500",
      "exhibits": "9 "
    },
    "star2": {
      "price": "4,200",
      "exhibits": "6 "
    },
    "id": "1640"
  },
  {
    "time": "14/02/20 03時",
    "star1": {
      "price": "4,300",
      "exhibits": "15 "
    },
    "star0": {
      "price": "--",
      "exhibits": "--"
    },
    "star3": {
      "price": "5,300",
      "exhibits": "10 "
    },
    "star2": {
      "price": "4,100",
      "exhibits": "12 "
    },
    "id": "1640"
  },
  {
    "time": "14/02/19 15時",
    "star1": {
      "price": "4,080",
      "exhibits": "13 "
    },
    "star0": {
      "price": "",
      "exhibits": ""
    },
    "star3": {
      "price": "5,190",
      "exhibits": "12 "
    },
    "star2": {
      "price": "4,100",
      "exhibits": "11 "
    },
    "id": "1640"
  },
  {
    "time": "14/02/18 15時",
    "star1": {
      "price": "4,300",
      "exhibits": "14 "
    },
    "star0": {
      "price": "5,500",
      "exhibits": "1 "
    },
    "star3": {
      "price": "5,300",
      "exhibits": "13 "
    },
    "star2": {
      "price": "4,100",
      "exhibits": "10 "
    },
    "id": "1640"
  },
  {
    "time": "14/02/18 03時",
    "star1": {
      "price": "4,200",
      "exhibits": "18 "
    },
    "star0": {
      "price": "3,000",
      "exhibits": "3 "
    },
    "star3": {
      "price": "5,560",
      "exhibits": "8 "
    },
    "star2": {
      "price": "4,100",
      "exhibits": "11 "
    },
    "id": "1640"
  },
  {
    "time": "14/02/17 15時",
    "star1": {
      "price": "4,100",
      "exhibits": "22 "
    },
    "star0": {
      "price": "5,500",
      "exhibits": "4 "
    },
    "star3": {
      "price": "5,800",
      "exhibits": "4 "
    },
    "star2": {
      "price": "4,100",
      "exhibits": "19 "
    },
    "id": "1640"
  },
  {
    "time": "14/02/17 03時",
    "star1": {
      "price": "4,300",
      "exhibits": "17 "
    },
    "star0": {
      "price": "5,000",
      "exhibits": "6 "
    },
    "star3": {
      "price": "5,500",
      "exhibits": "9 "
    },
    "star2": {
      "price": "4,100",
      "exhibits": "16 "
    },
    "id": "1640"
  },
  {
    "time": "14/02/16 15時",
    "star1": {
      "price": "4,000",
      "exhibits": "8 "
    },
    "star0": {
      "price": "",
      "exhibits": ""
    },
    "star3": {
      "price": "5,500",
      "exhibits": "10 "
    },
    "star2": {
      "price": "4,150",
      "exhibits": "13 "
    },
    "id": "1640"
  },
  {
    "time": "14/02/16 03時",
    "star1": {
      "price": "4,100",
      "exhibits": "6 "
    },
    "star0": {
      "price": "4,300",
      "exhibits": "2 "
    },
    "star3": {
      "price": "5,750",
      "exhibits": "9 "
    },
    "star2": {
      "price": "4,200",
      "exhibits": "7 "
    },
    "id": "1640"
  },
  {
    "time": "14/02/15 15時",
    "star1": {
      "price": "4,300",
      "exhibits": "12 "
    },
    "star0": {
      "price": "4,400",
      "exhibits": "2 "
    },
    "star3": {
      "price": "6,200",
      "exhibits": "3 "
    },
    "star2": {
      "price": "4,200",
      "exhibits": "6 "
    },
    "id": "1640"
  },
  {
    "time": "14/02/15 03時",
    "star1": {
      "price": "4,400",
      "exhibits": "6 "
    },
    "star0": {
      "price": "4,400",
      "exhibits": "2 "
    },
    "star3": {
      "price": "5,100",
      "exhibits": "8 "
    },
    "star2": {
      "price": "--",
      "exhibits": "--"
    },
    "id": "1640"
  },
  {
    "time": "14/02/14 15時",
    "star1": {
      "price": "4,000",
      "exhibits": "13 "
    },
    "star0": {
      "price": "4,400",
      "exhibits": "7 "
    },
    "star3": {
      "price": "5,280",
      "exhibits": "10 "
    },
    "star2": {
      "price": "4,000",
      "exhibits": "15 "
    },
    "id": "1640"
  },
  {
    "time": "14/02/14 03時",
    "star1": {
      "price": "4,270",
      "exhibits": "6 "
    },
    "star0": {
      "price": "--",
      "exhibits": "--"
    },
    "star3": {
      "price": "5,280",
      "exhibits": "14 "
    },
    "star2": {
      "price": "4,100",
      "exhibits": "10 "
    },
    "id": "1640"
  },
  {
    "time": "14/02/13 15時",
    "star1": {
      "price": "3,800",
      "exhibits": "20 "
    },
    "star0": {
      "price": "4,000",
      "exhibits": "1 "
    },
    "star3": {
      "price": "6,000",
      "exhibits": "14 "
    },
    "star2": {
      "price": "4,000",
      "exhibits": "30 "
    },
    "id": "1640"
  },
  {
    "time": "14/02/13 03時",
    "star1": {
      "price": "3,800",
      "exhibits": "29 "
    },
    "star0": {
      "price": "--",
      "exhibits": "--"
    },
    "star3": {
      "price": "6,600",
      "exhibits": "13 "
    },
    "star2": {
      "price": "4,100",
      "exhibits": "25 "
    },
    "id": "1640"
  },
  {
    "time": "14/02/12 15時",
    "star1": {
      "price": "4,270",
      "exhibits": "21 "
    },
    "star0": {
      "price": "4,800",
      "exhibits": "4 "
    },
    "star3": {
      "price": "6,790",
      "exhibits": "10 "
    },
    "star2": {
      "price": "4,300",
      "exhibits": "24 "
    },
    "id": "1640"
  },
  {
    "time": "14/02/12 03時",
    "star1": {
      "price": "4,300",
      "exhibits": "15 "
    },
    "star0": {
      "price": "5,650",
      "exhibits": "2 "
    },
    "star3": {
      "price": "6,800",
      "exhibits": "9 "
    },
    "star2": {
      "price": "4,300",
      "exhibits": "22 "
    },
    "id": "1640"
  },
  {
    "time": "14/02/11 15時",
    "star1": {
      "price": "4,400",
      "exhibits": "8 "
    },
    "star0": {
      "price": "4,400",
      "exhibits": "1 "
    },
    "star3": {
      "price": "6,900",
      "exhibits": "6 "
    },
    "star2": {
      "price": "4,400",
      "exhibits": "6 "
    },
    "id": "1640"
  },
  {
    "time": "14/02/11 04時",
    "star1": {
      "price": "4,400",
      "exhibits": "10 "
    },
    "star0": {
      "price": "4,400",
      "exhibits": "1 "
    },
    "star3": {
      "price": "12,000",
      "exhibits": "2 "
    },
    "star2": {
      "price": "4,210",
      "exhibits": "19 "
    },
    "id": "1640"
  },
  {
    "time": "14/02/10 15時",
    "star1": {
      "price": "4,400",
      "exhibits": "15 "
    },
    "star0": {
      "price": "4,400",
      "exhibits": "2 "
    },
    "star3": {
      "price": "5,800",
      "exhibits": "4 "
    },
    "star2": {
      "price": "4,400",
      "exhibits": "8 "
    },
    "id": "1640"
  },
  {
    "time": "14/02/10 03時",
    "star1": {
      "price": "4,400",
      "exhibits": "15 "
    },
    "star0": {
      "price": "--",
      "exhibits": "--"
    },
    "star3": {
      "price": "5,900",
      "exhibits": "4 "
    },
    "star2": {
      "price": "4,500",
      "exhibits": "6 "
    },
    "id": "1640"
  },
  {
    "time": "14/02/09 15時",
    "star1": {
      "price": "4,500",
      "exhibits": "5 "
    },
    "star0": {
      "price": "5,700",
      "exhibits": "4 "
    },
    "star3": {
      "price": "5,500",
      "exhibits": "12 "
    },
    "star2": {
      "price": "4,200",
      "exhibits": "4 "
    },
    "id": "1640"
  },
  {
    "time": "14/02/09 03時",
    "star1": {
      "price": "4,100",
      "exhibits": "5 "
    },
    "star0": {
      "price": "5,500",
      "exhibits": "5 "
    },
    "star3": {
      "price": "5,600",
      "exhibits": "20 "
    },
    "star2": {
      "price": "4,200",
      "exhibits": "5 "
    },
    "id": "1640"
  },
  {
    "time": "14/02/08 15時",
    "star1": {
      "price": "4,600",
      "exhibits": "9 "
    },
    "star0": {
      "price": "4,500",
      "exhibits": "2 "
    },
    "star3": {
      "price": "6,300",
      "exhibits": "14 "
    },
    "star2": {
      "price": "4,200",
      "exhibits": "5 "
    },
    "id": "1640"
  },
  {
    "time": "14/02/08 03時",
    "star1": {
      "price": "5,000",
      "exhibits": "4 "
    },
    "star0": {
      "price": "5,000",
      "exhibits": "3 "
    },
    "star3": {
      "price": "6,800",
      "exhibits": "14 "
    },
    "star2": {
      "price": "--",
      "exhibits": "--"
    },
    "id": "1640"
  },
  {
    "time": "14/02/07 15時",
    "star1": {
      "price": "4,100",
      "exhibits": "10 "
    },
    "star0": {
      "price": "4,100",
      "exhibits": "3 "
    },
    "star3": {
      "price": "7,980",
      "exhibits": "16 "
    },
    "star2": {
      "price": "4,100",
      "exhibits": "7 "
    },
    "id": "1640"
  },
  {
    "time": "14/02/07 03時",
    "star1": {
      "price": "4,200",
      "exhibits": "8 "
    },
    "star0": {
      "price": "--",
      "exhibits": "--"
    },
    "star3": {
      "price": "10,000",
      "exhibits": "16 "
    },
    "star2": {
      "price": "4,100",
      "exhibits": "10 "
    },
    "id": "1640"
  },
  {
    "time": "14/02/06 16時",
    "star1": {
      "price": "4,200",
      "exhibits": "10 "
    },
    "star0": {
      "price": "--",
      "exhibits": "--"
    },
    "star3": {
      "price": "10,000",
      "exhibits": "16 "
    },
    "star2": {
      "price": "4,200",
      "exhibits": "8 "
    },
    "id": "1640"
  },
  {
    "time": "14/02/06 03時",
    "star1": {
      "price": "4,200",
      "exhibits": "21 "
    },
    "star0": {
      "price": "4,300",
      "exhibits": "5 "
    },
    "star3": {
      "price": "15,000",
      "exhibits": "15 "
    },
    "star2": {
      "price": "4,200",
      "exhibits": "10 "
    },
    "id": "1640"
  },
  {
    "time": "14/02/05 15時",
    "star1": {
      "price": "4,300",
      "exhibits": "21 "
    },
    "star0": {
      "price": "4,300",
      "exhibits": "6 "
    },
    "star3": {
      "price": "15,000",
      "exhibits": "14 "
    },
    "star2": {
      "price": "4,100",
      "exhibits": "11 "
    },
    "id": "1640"
  },
  {
    "time": "14/02/05 03時",
    "star1": {
      "price": "4,380",
      "exhibits": "12 "
    },
    "star0": {
      "price": "4,500",
      "exhibits": "3 "
    },
    "star3": {
      "price": "16,000",
      "exhibits": "11 "
    },
    "star2": {
      "price": "4,500",
      "exhibits": "9 "
    },
    "id": "1640"
  },
  {
    "time": "14/02/04 15時",
    "star1": {
      "price": "4,300",
      "exhibits": "25 "
    },
    "star0": {
      "price": "4,300",
      "exhibits": "7 "
    },
    "star3": {
      "price": "17,800",
      "exhibits": "6 "
    },
    "star2": {
      "price": "4,200",
      "exhibits": "15 "
    },
    "id": "1640"
  },
  {
    "time": "14/02/04 03時",
    "star1": {
      "price": "4,600",
      "exhibits": "26 "
    },
    "star0": {
      "price": "4,500",
      "exhibits": "6 "
    },
    "star3": {
      "price": "19,900",
      "exhibits": "2 "
    },
    "star2": {
      "price": "4,500",
      "exhibits": "15 "
    },
    "id": "1640"
  },
  {
    "time": "14/02/03 18時",
    "star1": {
      "price": "4,600",
      "exhibits": "25 "
    },
    "star0": {
      "price": "4,500",
      "exhibits": "4 "
    },
    "star3": {
      "price": "19,900",
      "exhibits": "2 "
    },
    "star2": {
      "price": "5,000",
      "exhibits": "12 "
    },
    "id": "1640"
  },
  {
    "time": "14/02/03 03時",
    "star1": {
      "price": "5,500",
      "exhibits": "11 "
    },
    "star0": {
      "price": "5,500",
      "exhibits": "2 "
    },
    "star3": {
      "price": "5,200",
      "exhibits": "2 "
    },
    "star2": {
      "price": "5,200",
      "exhibits": "8 "
    },
    "id": "1640"
  },
  {
    "time": "14/02/02 15時",
    "star1": {
      "price": "4,950",
      "exhibits": "21 "
    },
    "star0": {
      "price": "4,500",
      "exhibits": "4 "
    },
    "star3": {
      "price": "5,000",
      "exhibits": "9 "
    },
    "star2": {
      "price": "3,990",
      "exhibits": "14 "
    },
    "id": "1640"
  },
  {
    "time": "14/02/02 03時",
    "star1": {
      "price": "5,200",
      "exhibits": "24 "
    },
    "star0": {
      "price": "5,200",
      "exhibits": "5 "
    },
    "star3": {
      "price": "17,000",
      "exhibits": "7 "
    },
    "star2": {
      "price": "3,700",
      "exhibits": "17 "
    },
    "id": "1640"
  },
  {
    "time": "14/02/01 17時",
    "star1": {
      "price": "5,500",
      "exhibits": "13 "
    },
    "star0": {
      "price": "5,500",
      "exhibits": "3 "
    },
    "star3": {
      "price": "17,000",
      "exhibits": "4 "
    },
    "star2": {
      "price": "5,490",
      "exhibits": "8 "
    },
    "id": "1640"
  },
  {
    "time": "14/02/01 03時",
    "star1": {
      "price": "--",
      "exhibits": "--"
    },
    "star0": {
      "price": "",
      "exhibits": ""
    },
    "star3": {
      "price": "6,400",
      "exhibits": "3 "
    },
    "star2": {
      "price": "6,480",
      "exhibits": "3 "
    },
    "id": "1640"
  }
]