[
  {
    "time": "15/04/16 16時",
    "star1": {
      "price": "8,700",
      "exhibits": "26 "
    },
    "star0": {
      "price": "500",
      "exhibits": "6 "
    },
    "star3": {
      "price": "",
      "exhibits": ""
    },
    "star2": {
      "price": "13,200",
      "exhibits": "68 "
    },
    "id": "4169"
  },
  {
    "time": "15/04/16 04時",
    "star1": {
      "price": "10,000",
      "exhibits": "8 "
    },
    "star0": {
      "price": "799",
      "exhibits": "3 "
    },
    "star3": {
      "price": "20,000",
      "exhibits": "32 "
    },
    "star2": {
      "price": "13,900",
      "exhibits": "24 "
    },
    "id": "4169"
  },
  {
    "time": "15/04/15 16時",
    "star1": {
      "price": "2,200",
      "exhibits": "19 "
    },
    "star0": {
      "price": "800",
      "exhibits": "9 "
    },
    "star3": {
      "price": "20,000",
      "exhibits": "51 "
    },
    "star2": {
      "price": "10,300",
      "exhibits": "19 "
    },
    "id": "4169"
  },
  {
    "time": "15/04/15 04時",
    "star1": {
      "price": "2,990",
      "exhibits": "11 "
    },
    "star0": {
      "price": "800",
      "exhibits": "8 "
    },
    "star3": {
      "price": "21,900",
      "exhibits": "56 "
    },
    "star2": {
      "price": "10,800",
      "exhibits": "25 "
    },
    "id": "4169"
  },
  {
    "time": "15/04/14 16時",
    "star1": {
      "price": "2,200",
      "exhibits": "24 "
    },
    "star0": {
      "price": "800",
      "exhibits": "9 "
    },
    "star3": {
      "price": "18,000",
      "exhibits": "19 "
    },
    "star2": {
      "price": "10,500",
      "exhibits": "48 "
    },
    "id": "4169"
  },
  {
    "time": "15/04/14 04時",
    "star1": {
      "price": "2,200",
      "exhibits": "19 "
    },
    "star0": {
      "price": "800",
      "exhibits": "11 "
    },
    "star3": {
      "price": "19,000",
      "exhibits": "37 "
    },
    "star2": {
      "price": "10,800",
      "exhibits": "33 "
    },
    "id": "4169"
  },
  {
    "time": "15/04/13 16時",
    "star1": {
      "price": "2,200",
      "exhibits": "41 "
    },
    "star0": {
      "price": "800",
      "exhibits": "10 "
    },
    "star3": {
      "price": "",
      "exhibits": ""
    },
    "star2": {
      "price": "10,600",
      "exhibits": "49 "
    },
    "id": "4169"
  },
  {
    "time": "15/04/13 04時",
    "star1": {
      "price": "2,280",
      "exhibits": "32 "
    },
    "star0": {
      "price": "900",
      "exhibits": "11 "
    },
    "star3": {
      "price": "",
      "exhibits": ""
    },
    "star2": {
      "price": "10,800",
      "exhibits": "57 "
    },
    "id": "4169"
  },
  {
    "time": "15/04/12 16時",
    "star1": {
      "price": "2,500",
      "exhibits": "19 "
    },
    "star0": {
      "price": "990",
      "exhibits": "12 "
    },
    "star3": {
      "price": "",
      "exhibits": ""
    },
    "star2": {
      "price": "10,800",
      "exhibits": "69 "
    },
    "id": "4169"
  },
  {
    "time": "15/04/12 04時",
    "star1": {
      "price": "2,960",
      "exhibits": "7 "
    },
    "star0": {
      "price": "900",
      "exhibits": "18 "
    },
    "star3": {
      "price": "24,800",
      "exhibits": "14 "
    },
    "star2": {
      "price": "12,000",
      "exhibits": "61 "
    },
    "id": "4169"
  },
  {
    "time": "15/04/11 16時",
    "star1": {
      "price": "2,100",
      "exhibits": "18 "
    },
    "star0": {
      "price": "990",
      "exhibits": "21 "
    },
    "star3": {
      "price": "",
      "exhibits": ""
    },
    "star2": {
      "price": "11,000",
      "exhibits": "61 "
    },
    "id": "4169"
  },
  {
    "time": "15/04/11 04時",
    "star1": {
      "price": "2,490",
      "exhibits": "19 "
    },
    "star0": {
      "price": "1,400",
      "exhibits": "16 "
    },
    "star3": {
      "price": "",
      "exhibits": ""
    },
    "star2": {
      "price": "11,400",
      "exhibits": "65 "
    },
    "id": "4169"
  },
  {
    "time": "15/04/10 16時",
    "star1": {
      "price": "1,700",
      "exhibits": "56 "
    },
    "star0": {
      "price": "1,500",
      "exhibits": "13 "
    },
    "star3": {
      "price": "",
      "exhibits": ""
    },
    "star2": {
      "price": "11,100",
      "exhibits": "31 "
    },
    "id": "4169"
  },
  {
    "time": "15/04/10 04時",
    "star1": {
      "price": "2,000",
      "exhibits": "46 "
    },
    "star0": {
      "price": "1,980",
      "exhibits": "11 "
    },
    "star3": {
      "price": "",
      "exhibits": ""
    },
    "star2": {
      "price": "12,500",
      "exhibits": "43 "
    },
    "id": "4169"
  },
  {
    "time": "15/04/09 16時",
    "star1": {
      "price": "3,000",
      "exhibits": "33 "
    },
    "star0": {
      "price": "2,000",
      "exhibits": "5 "
    },
    "star3": {
      "price": "26,900",
      "exhibits": "8 "
    },
    "star2": {
      "price": "10,500",
      "exhibits": "54 "
    },
    "id": "4169"
  },
  {
    "time": "15/04/08 16時",
    "star1": {
      "price": "3,400",
      "exhibits": "11 "
    },
    "star0": {
      "price": "",
      "exhibits": ""
    },
    "star3": {
      "price": "25,000",
      "exhibits": "19 "
    },
    "star2": {
      "price": "11,000",
      "exhibits": "19 "
    },
    "id": "4169"
  },
  {
    "time": "15/04/08 04時",
    "star1": {
      "price": "3,000",
      "exhibits": "28 "
    },
    "star0": {
      "price": "",
      "exhibits": ""
    },
    "star3": {
      "price": "26,200",
      "exhibits": "30 "
    },
    "star2": {
      "price": "11,000",
      "exhibits": "20 "
    },
    "id": "4169"
  },
  {
    "time": "15/04/07 16時",
    "star1": {
      "price": "3,000",
      "exhibits": "38 "
    },
    "star0": {
      "price": "1,600",
      "exhibits": "1 "
    },
    "star3": {
      "price": "26,000",
      "exhibits": "37 "
    },
    "star2": {
      "price": "11,000",
      "exhibits": "24 "
    },
    "id": "4169"
  },
  {
    "time": "15/04/07 04時",
    "star1": {
      "price": "3,580",
      "exhibits": "28 "
    },
    "star0": {
      "price": "1,600",
      "exhibits": "2 "
    },
    "star3": {
      "price": "27,500",
      "exhibits": "45 "
    },
    "star2": {
      "price": "11,800",
      "exhibits": "11 "
    },
    "id": "4169"
  },
  {
    "time": "15/04/06 16時",
    "star1": {
      "price": "3,300",
      "exhibits": "44 "
    },
    "star0": {
      "price": "500",
      "exhibits": "8 "
    },
    "star3": {
      "price": "24,500",
      "exhibits": "9 "
    },
    "star2": {
      "price": "9,900",
      "exhibits": "39 "
    },
    "id": "4169"
  },
  {
    "time": "15/04/06 04時",
    "star1": {
      "price": "3,600",
      "exhibits": "44 "
    },
    "star0": {
      "price": "500",
      "exhibits": "4 "
    },
    "star3": {
      "price": "26,200",
      "exhibits": "26 "
    },
    "star2": {
      "price": "10,500",
      "exhibits": "26 "
    },
    "id": "4169"
  },
  {
    "time": "15/04/05 16時",
    "star1": {
      "price": "3,980",
      "exhibits": "48 "
    },
    "star0": {
      "price": "1,600",
      "exhibits": "6 "
    },
    "star3": {
      "price": "",
      "exhibits": ""
    },
    "star2": {
      "price": "11,000",
      "exhibits": "46 "
    },
    "id": "4169"
  },
  {
    "time": "15/04/05 04時",
    "star1": {
      "price": "4,500",
      "exhibits": "45 "
    },
    "star0": {
      "price": "2,200",
      "exhibits": "5 "
    },
    "star3": {
      "price": "30,000",
      "exhibits": "15 "
    },
    "star2": {
      "price": "12,100",
      "exhibits": "35 "
    },
    "id": "4169"
  },
  {
    "time": "15/04/04 16時",
    "star1": {
      "price": "4,590",
      "exhibits": "65 "
    },
    "star0": {
      "price": "2,200",
      "exhibits": "6 "
    },
    "star3": {
      "price": "",
      "exhibits": ""
    },
    "star2": {
      "price": "9,900",
      "exhibits": "29 "
    },
    "id": "4169"
  },
  {
    "time": "15/04/04 04時",
    "star1": {
      "price": "5,200",
      "exhibits": "36 "
    },
    "star0": {
      "price": "3,000",
      "exhibits": "4 "
    },
    "star3": {
      "price": "",
      "exhibits": ""
    },
    "star2": {
      "price": "11,400",
      "exhibits": "60 "
    },
    "id": "4169"
  },
  {
    "time": "15/04/03 16時",
    "star1": {
      "price": "6,400",
      "exhibits": "41 "
    },
    "star0": {
      "price": "3,000",
      "exhibits": "6 "
    },
    "star3": {
      "price": "",
      "exhibits": ""
    },
    "star2": {
      "price": "11,000",
      "exhibits": "53 "
    },
    "id": "4169"
  },
  {
    "time": "15/04/03 04時",
    "star1": {
      "price": "6,900",
      "exhibits": "29 "
    },
    "star0": {
      "price": "3,000",
      "exhibits": "5 "
    },
    "star3": {
      "price": "",
      "exhibits": ""
    },
    "star2": {
      "price": "11,500",
      "exhibits": "66 "
    },
    "id": "4169"
  },
  {
    "time": "15/04/02 16時",
    "star1": {
      "price": "7,680",
      "exhibits": "10 "
    },
    "star0": {
      "price": "6,000",
      "exhibits": "1 "
    },
    "star3": {
      "price": "21,400",
      "exhibits": "31 "
    },
    "star2": {
      "price": "12,700",
      "exhibits": "39 "
    },
    "id": "4169"
  },
  {
    "time": "15/04/01 16時",
    "star1": {
      "price": "5,000",
      "exhibits": "2 "
    },
    "star0": {
      "price": "400",
      "exhibits": "2 "
    },
    "star3": {
      "price": "22,000",
      "exhibits": "35 "
    },
    "star2": {
      "price": "9,200",
      "exhibits": "41 "
    },
    "id": "4169"
  },
  {
    "time": "15/04/01 04時",
    "star1": {
      "price": "5,000",
      "exhibits": "5 "
    },
    "star0": {
      "price": "400",
      "exhibits": "3 "
    },
    "star3": {
      "price": "25,000",
      "exhibits": "38 "
    },
    "star2": {
      "price": "10,000",
      "exhibits": "42 "
    },
    "id": "4169"
  }
]