[
  {
    "time": "15/04/11 00時",
    "star1": {
      "price": "350",
      "exhibits": "51 "
    },
    "star0": {
      "price": "285",
      "exhibits": "18 "
    },
    "star3": {
      "price": "",
      "exhibits": ""
    },
    "star2": {
      "price": "1,870",
      "exhibits": "31 "
    },
    "id": "636"
  },
  {
    "time": "15/04/10 12時",
    "star1": {
      "price": "419",
      "exhibits": "57 "
    },
    "star0": {
      "price": "250",
      "exhibits": "26 "
    },
    "star3": {
      "price": "",
      "exhibits": ""
    },
    "star2": {
      "price": "",
      "exhibits": ""
    },
    "id": "636"
  },
  {
    "time": "15/04/10 00時",
    "star1": {
      "price": "417",
      "exhibits": "60 "
    },
    "star0": {
      "price": "285",
      "exhibits": "22 "
    },
    "star3": {
      "price": "",
      "exhibits": ""
    },
    "star2": {
      "price": "",
      "exhibits": ""
    },
    "id": "636"
  },
  {
    "time": "15/04/09 12時",
    "star1": {
      "price": "500",
      "exhibits": "30 "
    },
    "star0": {
      "price": "270",
      "exhibits": "23 "
    },
    "star3": {
      "price": "",
      "exhibits": ""
    },
    "star2": {
      "price": "1,470",
      "exhibits": "28 "
    },
    "id": "636"
  },
  {
    "time": "15/04/09 00時",
    "star1": {
      "price": "450",
      "exhibits": "43 "
    },
    "star0": {
      "price": "280",
      "exhibits": "20 "
    },
    "star3": {
      "price": "",
      "exhibits": ""
    },
    "star2": {
      "price": "2,500",
      "exhibits": "14 "
    },
    "id": "636"
  },
  {
    "time": "15/04/08 12時",
    "star1": {
      "price": "700",
      "exhibits": "31 "
    },
    "star0": {
      "price": "300",
      "exhibits": "7 "
    },
    "star3": {
      "price": "",
      "exhibits": ""
    },
    "star2": {
      "price": "3,900",
      "exhibits": "16 "
    },
    "id": "636"
  },
  {
    "time": "15/04/08 00時",
    "star1": {
      "price": "478",
      "exhibits": "49 "
    },
    "star0": {
      "price": "299",
      "exhibits": "7 "
    },
    "star3": {
      "price": "",
      "exhibits": ""
    },
    "star2": {
      "price": "1,600",
      "exhibits": "28 "
    },
    "id": "636"
  },
  {
    "time": "15/04/07 12時",
    "star1": {
      "price": "499",
      "exhibits": "19 "
    },
    "star0": {
      "price": "300",
      "exhibits": "9 "
    },
    "star3": {
      "price": "",
      "exhibits": ""
    },
    "star2": {
      "price": "2,200",
      "exhibits": "26 "
    },
    "id": "636"
  },
  {
    "time": "15/04/07 00時",
    "star1": {
      "price": "452",
      "exhibits": "41 "
    },
    "star0": {
      "price": "250",
      "exhibits": "12 "
    },
    "star3": {
      "price": "",
      "exhibits": ""
    },
    "star2": {
      "price": "1,480",
      "exhibits": "33 "
    },
    "id": "636"
  },
  {
    "time": "15/04/06 12時",
    "star1": {
      "price": "849",
      "exhibits": "12 "
    },
    "star0": {
      "price": "232",
      "exhibits": "20 "
    },
    "star3": {
      "price": "",
      "exhibits": ""
    },
    "star2": {
      "price": "1,800",
      "exhibits": "34 "
    },
    "id": "636"
  },
  {
    "time": "15/04/06 00時",
    "star1": {
      "price": "448",
      "exhibits": "61 "
    },
    "star0": {
      "price": "270",
      "exhibits": "16 "
    },
    "star3": {
      "price": "",
      "exhibits": ""
    },
    "star2": {
      "price": "1,440",
      "exhibits": "20 "
    },
    "id": "636"
  },
  {
    "time": "15/04/05 12時",
    "star1": {
      "price": "500",
      "exhibits": "31 "
    },
    "star0": {
      "price": "200",
      "exhibits": "18 "
    },
    "star3": {
      "price": "",
      "exhibits": ""
    },
    "star2": {
      "price": "2,190",
      "exhibits": "34 "
    },
    "id": "636"
  },
  {
    "time": "15/04/05 00時",
    "star1": {
      "price": "400",
      "exhibits": "42 "
    },
    "star0": {
      "price": "260",
      "exhibits": "14 "
    },
    "star3": {
      "price": "",
      "exhibits": ""
    },
    "star2": {
      "price": "1,450",
      "exhibits": "34 "
    },
    "id": "636"
  },
  {
    "time": "15/04/04 12時",
    "star1": {
      "price": "590",
      "exhibits": "40 "
    },
    "star0": {
      "price": "390",
      "exhibits": "8 "
    },
    "star3": {
      "price": "",
      "exhibits": ""
    },
    "star2": {
      "price": "3,000",
      "exhibits": "36 "
    },
    "id": "636"
  },
  {
    "time": "15/04/04 00時",
    "star1": {
      "price": "398",
      "exhibits": "45 "
    },
    "star0": {
      "price": "300",
      "exhibits": "17 "
    },
    "star3": {
      "price": "",
      "exhibits": ""
    },
    "star2": {
      "price": "1,400",
      "exhibits": "36 "
    },
    "id": "636"
  },
  {
    "time": "15/04/03 12時",
    "star1": {
      "price": "800",
      "exhibits": "31 "
    },
    "star0": {
      "price": "400",
      "exhibits": "12 "
    },
    "star3": {
      "price": "",
      "exhibits": ""
    },
    "star2": {
      "price": "2,890",
      "exhibits": "53 "
    },
    "id": "636"
  },
  {
    "time": "15/04/03 00時",
    "star1": {
      "price": "500",
      "exhibits": "50 "
    },
    "star0": {
      "price": "400",
      "exhibits": "11 "
    },
    "star3": {
      "price": "",
      "exhibits": ""
    },
    "star2": {
      "price": "1,800",
      "exhibits": "24 "
    },
    "id": "636"
  },
  {
    "time": "15/04/02 12時",
    "star1": {
      "price": "490",
      "exhibits": "32 "
    },
    "star0": {
      "price": "299",
      "exhibits": "17 "
    },
    "star3": {
      "price": "",
      "exhibits": ""
    },
    "star2": {
      "price": "1,000",
      "exhibits": "49 "
    },
    "id": "636"
  },
  {
    "time": "15/04/02 00時",
    "star1": {
      "price": "450",
      "exhibits": "44 "
    },
    "star0": {
      "price": "285",
      "exhibits": "22 "
    },
    "star3": {
      "price": "",
      "exhibits": ""
    },
    "star2": {
      "price": "1,390",
      "exhibits": "29 "
    },
    "id": "636"
  },
  {
    "time": "15/04/01 12時",
    "star1": {
      "price": "600",
      "exhibits": "20 "
    },
    "star0": {
      "price": "170",
      "exhibits": "20 "
    },
    "star3": {
      "price": "",
      "exhibits": ""
    },
    "star2": {
      "price": "2,980",
      "exhibits": "57 "
    },
    "id": "636"
  },
  {
    "time": "15/04/01 00時",
    "star1": {
      "price": "499",
      "exhibits": "41 "
    },
    "star0": {
      "price": "200",
      "exhibits": "18 "
    },
    "star3": {
      "price": "",
      "exhibits": ""
    },
    "star2": {
      "price": "1,930",
      "exhibits": "29 "
    },
    "id": "636"
  }
]